wts_nerdler/__init__.py
wts_nerdler/windows_task_scheduler.py
wts_nerdler-1.1.0.dist-info/METADATA
wts_nerdler-1.1.0.dist-info/WHEEL
wts_nerdler-1.1.0.dist-info/top_level.txt
wts_nerdler-1.1.0.dist-info/RECORD
